fsl/__init__.py
fsl/gui/__init__.py
fsl/gui/core.py
fsl/gui/exceptions.py
fsl/gui/guis.py
fsl/gui/icons.py
fsl/gui/tools.py
fsl/gui/views.py
fsl/gui/widgets.py
fsl/gui/icons/add.png
fsl/gui/icons/add@2x.png
fsl/gui/icons/clear.png
fsl/gui/icons/clear@2x.png
fsl/gui/icons/code.png
fsl/gui/icons/code@2x.png
fsl/gui/icons/detach.png
fsl/gui/icons/detach@2x.png
fsl/gui/icons/download.png
fsl/gui/icons/download@2x.png
fsl/gui/icons/explore.png
fsl/gui/icons/explore@2x.png
fsl/gui/icons/fsl-logo-x2.png
fsl/gui/icons/help.png
fsl/gui/icons/help@2x.png
fsl/gui/icons/open_folder.png
fsl/gui/icons/open_folder@2x.png
fsl/gui/icons/pause.png
fsl/gui/icons/pause@2x.png
fsl/gui/icons/play.png
fsl/gui/icons/play@2x.png
fsl/gui/icons/play_all.png
fsl/gui/icons/play_all@2x.png
fsl/gui/icons/save.png
fsl/gui/icons/save@2x.png
fsl/gui/icons/settings.png
fsl/gui/icons/settings@2x.png
fsl/gui/icons/upload.png
fsl/gui/icons/upload@2x.png
fsl/gui/scripts/Bet_gui.py
fsl/gui/scripts/Flirt_gui.py
fsl/gui/scripts/__init__.py
fslgui-0.0.0.dev9.dist-info/LICENSE
fslgui-0.0.0.dev9.dist-info/METADATA
fslgui-0.0.0.dev9.dist-info/WHEEL
fslgui-0.0.0.dev9.dist-info/top_level.txt
fslgui-0.0.0.dev9.dist-info/RECORD
